level4/__init__.py
level4/__main__.py
level4/main.py
level4/model.py
level4/py.typed
level4/app/__init__.py
level4/app/__main__.py
level4/app/main.py
level4-0.0.4b0.dist-info/LICENSE
level4-0.0.4b0.dist-info/METADATA
level4-0.0.4b0.dist-info/WHEEL
level4-0.0.4b0.dist-info/top_level.txt
level4-0.0.4b0.dist-info/RECORD
