Metadata-Version: 2.1
Name: level4
Version: 0.0.4b0
Summary: "TBD"
Author: Spencer Young
Author-email: spencer.young@spyoung.com
Keywords: aws,cdk,iac,level4,cicd,github,gitlab
Classifier: Intended Audience :: Developers
Classifier: Programming Language :: Python
Classifier: Programming Language :: Python :: 3 :: Only
Classifier: Programming Language :: Python :: 3.10
Classifier: Programming Language :: Python :: 3.11
Requires-Python: >=3.10.0
License-File: LICENSE
Requires-Dist: pydantic
Requires-Dist: aws-cdk-lib
Requires-Dist: jinja2
